odoo/addons/shopinvader_api_cart_cancel/README.rst
odoo/addons/shopinvader_api_cart_cancel/__init__.py
odoo/addons/shopinvader_api_cart_cancel/__manifest__.py
odoo/addons/shopinvader_api_cart_cancel/i18n/shopinvader_api_cart_cancel.pot
odoo/addons/shopinvader_api_cart_cancel/readme/CONTRIBUTORS.rst
odoo/addons/shopinvader_api_cart_cancel/readme/DESCRIPTION.rst
odoo/addons/shopinvader_api_cart_cancel/routers/__init__.py
odoo/addons/shopinvader_api_cart_cancel/routers/cart.py
odoo/addons/shopinvader_api_cart_cancel/static/description/index.html
odoo/addons/shopinvader_api_cart_cancel/tests/__init__.py
odoo/addons/shopinvader_api_cart_cancel/tests/test_shopinvader_api_cart_cancel.py
odoo_addon_shopinvader_api_cart_cancel-16.0.1.0.0.1.dist-info/METADATA
odoo_addon_shopinvader_api_cart_cancel-16.0.1.0.0.1.dist-info/WHEEL
odoo_addon_shopinvader_api_cart_cancel-16.0.1.0.0.1.dist-info/top_level.txt
odoo_addon_shopinvader_api_cart_cancel-16.0.1.0.0.1.dist-info/RECORD
